graphql_sqlalchemy/__init__.py
graphql_sqlalchemy/args.py
graphql_sqlalchemy/dialects/__init__.py
graphql_sqlalchemy/dialects/pg/__init__.py
graphql_sqlalchemy/dialects/pg/inputs.py
graphql_sqlalchemy/graphql_types.py
graphql_sqlalchemy/helpers.py
graphql_sqlalchemy/inputs.py
graphql_sqlalchemy/names.py
graphql_sqlalchemy/objects.py
graphql_sqlalchemy/resolvers.py
graphql_sqlalchemy/schema.py
graphql_sqlalchemy/types.py
graphql_sqlalchemy-0.6.1.dist-info/LICENSE.md
graphql_sqlalchemy-0.6.1.dist-info/WHEEL
graphql_sqlalchemy-0.6.1.dist-info/METADATA
graphql_sqlalchemy-0.6.1.dist-info/RECORD
