Metadata-Version: 2.1
Name: graphql-sqlalchemy
Version: 0.6.1
Summary: Generate GraphQL Schemas from your SQLAlchemy models
Home-page: https://github.com/gzzo/graphql-sqlalchemy
License: MIT
Keywords: graphql,sqlalchemy
Author: Guido Rainuzzo
Author-email: hi@guido.nyc
Requires-Python: >=3.6.0,<4
Classifier: Intended Audience :: Developers
Classifier: License :: OSI Approved :: MIT License
Classifier: Programming Language :: Python :: 3
Classifier: Programming Language :: Python :: 3.6
Classifier: Programming Language :: Python :: 3.7
Classifier: Programming Language :: Python :: 3.8
Classifier: Programming Language :: Python :: 3.9
Classifier: Topic :: Software Development :: Libraries
Provides-Extra: docs
Requires-Dist: SQLAlchemy (>=1.3.0,<2.0.0)
Requires-Dist: graphql-core (>=3.0.0,<4)
Requires-Dist: pygments-graphql (>=1.0.0,<2.0.0); extra == "docs"
Requires-Dist: pygments-style-solarized (>=0.1.1,<1.0.0); extra == "docs"
Requires-Dist: sphinx (>=3.5.3,<4.0.0); extra == "docs"
Requires-Dist: sphinx-rtd-theme (>=0.5.1,<1.0.0); extra == "docs"
Project-URL: Repository, https://github.com/gzzo/graphql-sqlalchemy
